printout/__init__.py
printout/printout.py
printout-1.2.8.dist-info/licenses/LICENSE
printout-1.2.8.dist-info/METADATA
printout-1.2.8.dist-info/WHEEL
printout-1.2.8.dist-info/top_level.txt
printout-1.2.8.dist-info/RECORD
