Metadata-Version: 2.4
Name: printout
Version: 1.2.8
Summary: This print utility allows you to print information to the console and file in one call.  You don't need to use logger and print anymore.  With this tool, you can perform both actions using only printout
Author-email: Jelani Jenkins <jj@jenkinscode.com>
License: MIT
Project-URL: Homepage, https://github.com/jenkinscode1/printout
Project-URL: Documentation, https://printout.readthedocs.io
Project-URL: Source, https://github.com/jenkinscode1/printout
Project-URL: Issues, https://github.com/jenkinscode1/printout/issues
Requires-Python: >=3.7
License-File: LICENSE
Dynamic: license-file
